Mensajes/__init__.py
Mensajes/setup.py
Mensajes/Hola/__init__.py
Mensajes/Hola/saludos.py
Mensajes/adios/__init__.py
Mensajes/adios/despedidas.py
tests/__init__.py
tests/test_Hola.py
Mensajes_crispal-6.0.dist-info/LICENSE
Mensajes_crispal-6.0.dist-info/METADATA
Mensajes_crispal-6.0.dist-info/WHEEL
Mensajes_crispal-6.0.dist-info/top_level.txt
Mensajes_crispal-6.0.dist-info/RECORD
